{
 "attach_print": 0,
 "channel": "Email",
 "condition": "doc.send_email==1",
 "creation": "2022-12-22 11:56:33.959949",
 "days_in_advance": 0,
 "docstatus": 0,
 "doctype": "Notification",
 "document_type": "Notification Log",
 "enabled": 1,
 "event": "New",
 "idx": 0,
 "is_standard": 1,
 "message": "{{ doc.email_content }}",
 "modified": "2022-12-22 11:56:33.959949",
 "modified_by": "Administrator",
 "module": "Ohm Groups",
 "name": "Vehicle Log",
 "owner": "Administrator",
 "recipients": [
  {
   "receiver_by_document_field": "for_user"
  }
 ],
 "send_system_notification": 1,
 "send_to_all_assignees": 0,
 "sender": "",
 "sender_email": "",
 "subject": "{{ doc.subject }}"
}